requests_auth/__init__.py
requests_auth/authentication.py
requests_auth/errors.py
requests_auth/oauth2_authentication_responses_server.py
requests_auth/oauth2_tokens.py
requests_auth/testing.py
requests_auth/version.py
requests_auth-7.0.0.dist-info/LICENSE
requests_auth-7.0.0.dist-info/METADATA
requests_auth-7.0.0.dist-info/WHEEL
requests_auth-7.0.0.dist-info/top_level.txt
requests_auth-7.0.0.dist-info/RECORD
