Metadata-Version: 2.1
Name: requests-auth
Version: 7.0.0
Summary: Authentication for Requests
Author-email: Colin Bounouar <colin.bounouar.dev@gmail.com>
Maintainer-email: Colin Bounouar <colin.bounouar.dev@gmail.com>
License: MIT License
Project-URL: documentation, https://colin-b.github.io/requests_auth/
Project-URL: repository, https://github.com/Colin-b/requests_auth
Project-URL: changelog, https://github.com/Colin-b/requests_auth/blob/master/CHANGELOG.md
Project-URL: issues, https://github.com/Colin-b/requests_auth/issues
Keywords: authentication,ntlm,oauth2,azure-active-directory,azure-ad,okta,apikey,multiple
Classifier: Development Status :: 5 - Production/Stable
Classifier: Intended Audience :: Developers
Classifier: License :: OSI Approved :: MIT License
Classifier: Natural Language :: English
Classifier: Programming Language :: Python
Classifier: Programming Language :: Python :: 3
Classifier: Programming Language :: Python :: 3.7
Classifier: Programming Language :: Python :: 3.8
Classifier: Programming Language :: Python :: 3.9
Classifier: Programming Language :: Python :: 3.10
Classifier: Programming Language :: Python :: 3.11
Classifier: Topic :: Software Development :: Build Tools
Requires-Python: >=3.7
Provides-Extra: testing
License-File: LICENSE
